core_universal4-4.54.3.data/purelib/applitools/core_universal/__init__.py
core_universal4-4.54.3.data/purelib/applitools/core_universal/__main__.py
core_universal4-4.54.3.data/purelib/applitools/core_universal/instance.py
core_universal4-4.54.3.data/purelib/applitools/core_universal/server.py
core_universal4-4.54.3.data/purelib/applitools/core_universal/bin/core
core_universal4-4.54.3.dist-info/licenses/LICENSE
core_universal4-4.54.3.dist-info/METADATA
core_universal4-4.54.3.dist-info/WHEEL
core_universal4-4.54.3.dist-info/top_level.txt
core_universal4-4.54.3.dist-info/RECORD
