Metadata-Version: 2.4
Name: core-universal4
Version: 4.54.3
Summary: Applitools Eyes Core SDK Server
Author-email: Applitools Team <team@applitools.com>
License-Expression: LicenseRef-Proprietary
Project-URL: Homepage, https://applitools.com
Classifier: Programming Language :: Python
Classifier: Development Status :: 5 - Production/Stable
Classifier: Intended Audience :: Developers
Classifier: Operating System :: MacOS
Classifier: Operating System :: Microsoft :: Windows
Classifier: Operating System :: POSIX :: Linux
Classifier: Topic :: Software Development :: Quality Assurance
Classifier: Topic :: Software Development :: Testing
Requires-Python: <4,>=3.7
License-File: LICENSE
Requires-Dist: importlib-resources; python_version < "3.9"
Dynamic: license-file
